setup.py
Binomial_prob_pckg/Binomialdistribution.py
Binomial_prob_pckg/Binomialdistribution_challenge.py
Binomial_prob_pckg/test.py
Binomial_prob_pckg.egg-info/PKG-INFO
Binomial_prob_pckg.egg-info/SOURCES.txt
Binomial_prob_pckg.egg-info/dependency_links.txt
Binomial_prob_pckg.egg-info/not-zip-safe
Binomial_prob_pckg.egg-info/top_level.txt