Metadata-Version: 1.0
Name: Binomial-prob-pckg
Version: 0.1
Summary: Gaussian distributions
Home-page: UNKNOWN
Author: Tomiwa_salau
Author-email: ayotomiwasalau@gmail.com
License: UNKNOWN
Platform: UNKNOWN
